sl4a/__init__.py
sl4a/android.py
sl4a/apk/Py4A.apk
sl4a/apk/SL4A.apk
sl4a/example.txt
sl4a/rpc.py
sl4a/script.py
sl4a/scripts/SL4A-SERVER.py
sl4a-0.0.1.dist-info/LICENSE
sl4a-0.0.1.dist-info/METADATA
sl4a-0.0.1.dist-info/WHEEL
sl4a-0.0.1.dist-info/entry_points.txt
sl4a-0.0.1.dist-info/RECORD
