Metadata-Version: 2.1
Name: SL4A
Version: 0.0.1
Summary: Connect to Android via SL4A
Home-page: https://github.com/MainPlay-TG/SL4A.py
Author: MainPlay TG
Author-email: xbox.roman6666666666@gmail.com
Requires-Python: >=3.8,<4.0
Classifier: Programming Language :: Python :: 3
Classifier: Programming Language :: Python :: 3.8
Classifier: Programming Language :: Python :: 3.9
Classifier: Programming Language :: Python :: 3.10
Classifier: Programming Language :: Python :: 3.11
Classifier: Programming Language :: Python :: 3.12
Project-URL: Repository, https://github.com/MainPlay-TG/SL4A.py
